bytesop.pyd
BytesOp-0.10.dist-info/DESCRIPTION.rst
BytesOp-0.10.dist-info/METADATA
BytesOp-0.10.dist-info/RECORD
BytesOp-0.10.dist-info/WHEEL
BytesOp-0.10.dist-info/metadata.json
BytesOp-0.10.dist-info/top_level.txt
