Metadata-Version: 2.0
Name: BytesOp
Version: 0.10
Summary: Bitwise operations on bytestrings.
Home-page: https://github.com/janbrohl/BytesOp
Author: Jan Brohl
Author-email: janbrohl@t-online.de
License: UNKNOWN
Platform: UNKNOWN
Classifier: Development Status :: 3 - Alpha
Classifier: License :: OSI Approved :: BSD License
Classifier: Programming Language :: Python
Classifier: Programming Language :: Python :: 3
Classifier: Programming Language :: Python :: 2
Classifier: Programming Language :: C++
Classifier: Operating System :: OS Independent
Classifier: License :: OSI Approved
